ccs_fit/__init__.py
ccs_fit/ase_calculator/buck.py
ccs_fit/ase_calculator/ccs_ase_G2B.py
ccs_fit/ase_calculator/ccs_ase_calculator.py
ccs_fit/common/__init__.py
ccs_fit/common/exceptions.py
ccs_fit/common/io.py
ccs_fit/common/math/__init__.py
ccs_fit/common/math/ewald.py
ccs_fit/common/neighborlist.py
ccs_fit/data/__init__.py
ccs_fit/data/conversion.py
ccs_fit/debugging_tools/timing.py
ccs_fit/fitting/__init__.py
ccs_fit/fitting/main copy.py
ccs_fit/fitting/main.py
ccs_fit/fitting/objective.py
ccs_fit/fitting/spline_functions.py
ccs_fit/ppmd_interface/ccs_ppmd.py
ccs_fit/regression_tool/regression.py
ccs_fit/scripts/__init__.py
ccs_fit/scripts/ccs_build_db copy.py
ccs_fit/scripts/ccs_build_db.py
ccs_fit/scripts/ccs_export_FF.py
ccs_fit/scripts/ccs_export_sktable.py
ccs_fit/scripts/ccs_fetch.py
ccs_fit/scripts/ccs_fit.py
ccs_fit/scripts/ccs_prune.py
ccs_fit/scripts/ccs_validate.py
ccs_fit/scripts/jsonTotable.py
ccs_fit-0.22.5.dist-info/LICENSE
ccs_fit-0.22.5.dist-info/METADATA
ccs_fit-0.22.5.dist-info/WHEEL
ccs_fit-0.22.5.dist-info/entry_points.txt
ccs_fit-0.22.5.dist-info/RECORD
