Metadata-Version: 2.1
Name: ccs_fit
Version: 0.22.5
Summary: Fitting tools for repulsive two body interactions using curvature constrained splines.
Home-page: https://github.com/Teoroo-CMC/CCS
License: GPL-3
Keywords: Curvature,Constrained,Splines,Two-Body,Interatomic,Repulsive,Fitting
Author: Akshay Krishna AK
Maintainer: Jolla Kullgren
Maintainer-email: jolla.kullgren@kemi.uu.se
Requires-Python: >=3.8
Classifier: Development Status :: 4 - Beta
Classifier: License :: Other/Proprietary License
Classifier: Programming Language :: Python :: 3
Classifier: Programming Language :: Python :: 3.8
Classifier: Programming Language :: Python :: 3.9
Classifier: Programming Language :: Python :: 3.10
Classifier: Programming Language :: Python :: 3.11
Classifier: Programming Language :: Python :: 3.12
Requires-Dist: ase (>=3.22.1)
Requires-Dist: cvxopt (>=1.3.0)
Requires-Dist: numpy (>=1.22.4,<1.23.0)
Requires-Dist: pandas (>=1.5.0)
Requires-Dist: pyyaml (>=6.0)
Requires-Dist: scikit-learn (>=1.2.1,<2.0.0)
Requires-Dist: scipy (>=1.9.2)
Requires-Dist: sympy (>=1.11.1)
Requires-Dist: tqdm (>=4.64.1)
Project-URL: Documentation, https://teoroo-cmc.github.io/CCS/index.html
Project-URL: Repository, https://github.com/Teoroo-CMC/CCS
